Workbook
Name Aporte: Planilha2!$D$21
Name Qtde_anos: Planilha2!$D$22
Name rendimento_carteira: Planilha2!$D$17
Name salario: Planilha2!$B$16
Name sugestao_investimento: Planilha2!$B$18
Name taxa_mensal: Planilha2!$D$23

Sheet Planilha2
B15: CONFIGURAÇÕES
B16: Salário | D16: 5000
B17: Rendimento carteira | D17: 0.006
B18: Sugestão de Investimento | D18: =D16*30% -> 1500
B20: INVESTIMENTO MENSAL
B21: Quanto investir por mês? | D21: 500
B22: Por quantos anos? | D22: 5
B23: Taxa de rendimento mensal? | D23: 0.0108
B24: Patrimônio acumulado? | D24: =FV(taxa_mensal,Qtde_anos*12,Aporte*-1) -> 41902.01
B25: Dividendos mensais? | D25: =D24*rendimento_carteira -> 251.41206
B28: CENÁRIOS | D28: DIVIDENDOS
A29: 2 | B29: Quanto em 02 anos? | C29: =FV($D$23,$A29*12,$D$21*-1) -> 13615.432 | D29: =C29*rendimento_carteira -> 81.692591
A30: 5 | B30: Quanto em 05 anos? | C30: =FV($D$23,$A30*12,$D$21*-1) -> 41902.01 | D30: =C30*rendimento_carteira -> 251.41206
A31: 10 | B31: Quanto em 10 anos? | C31: =FV($D$23,$A31*12,$D$21*-1) -> 121728.83 | D31: =C31*rendimento_carteira -> 730.373
A32: 20 | B32: Quanto em 20 anos? | C32: =FV($D$23,$A32*12,$D$21*-1) -> 563524.5 | D32: =C32*rendimento_carteira -> 3381.147
A33: 30 | B33: Quanto em 30 anos? | C33: =FV($D$23,$A33*12,$D$21*-1) -> 2166952.4 | D33: =C33*rendimento_carteira -> 13001.714
B36: PERFIL | C36: CONSERVADOR
B37: VALOR A SER INVESTIDO POR MÊS | C37: =Aporte -> 500
B40: TIPO DE FII | C40: PERCENTUAL SUGERIDO | D40: VALORES
B41: PAPEL | C41: =VLOOKUP($C$36&"-"&B41,Planilha3!A4:D22,4,FALSE) -> 0.3 | D41: =C41*$C$37 -> 150
B42: TIJOLO | C42: =VLOOKUP($C$36&"-"&B42,Planilha3!A5:D23,4,FALSE) -> 0.5 | D42: =C42*$C$37 -> 250
B43: FOFs | C43: =VLOOKUP($C$36&"-"&B43,Planilha3!A6:D24,4,FALSE) -> 0.1 | D43: =C43*$C$37 -> 50
B44: HIBRIDOS | C44: =VLOOKUP($C$36&"-"&B44,Planilha3!A7:D25,4,FALSE) -> 0.1 | D44: =C44*$C$37 -> 50
B45: DESENVOLVIMENTO | C45: =VLOOKUP($C$36&"-"&B45,Planilha3!A8:D26,4,FALSE) -> 0 | D45: =C45*$C$37 -> 0
B46: HOTELARIAS | C46: =VLOOKUP($C$36&"-"&B46,Planilha3!A9:D27,4,FALSE) -> 0 | D46: =C46*$C$37 -> 0
D47: =SUM(D41:D46) -> 500

Sheet Planilha3
H3: %
A4: CHAVE | B4: PERFIL | C4: TIPO DE FII | D4: PERCENTUAL | G4: MODERADO-TIJOLO | H4: =VLOOKUP(G4,$A$4:$D$22,4,FALSE) -> 0.4
A5: =$B5&"-"&C5 -> CONSERVADOR-PAPEL | B5: CONSERVADOR | C5: PAPEL | D5: 0.3
A6: =$B6&"-"&C6 -> CONSERVADOR-TIJOLO | B6: CONSERVADOR | C6: TIJOLO | D6: 0.5
A7: =$B7&"-"&C7 -> CONSERVADOR-FOFs | B7: CONSERVADOR | C7: FOFs | D7: 0.1
A8: =$B8&"-"&C8 -> CONSERVADOR-HIBRIDOS | B8: CONSERVADOR | C8: HIBRIDOS | D8: 0.1
A9: =$B9&"-"&C9 -> CONSERVADOR-DESENVOLVIMENTO | B9: CONSERVADOR | C9: DESENVOLVIMENTO | D9: 0
A10: =$B10&"-"&C10 -> CONSERVADOR-HOTELARIAS | B10: CONSERVADOR | C10: HOTELARIAS | D10: 0
A11: =$B11&"-"&C11 -> MODERADO-PAPEL | B11: MODERADO | C11: PAPEL | D11: 0.32
A12: =$B12&"-"&C12 -> MODERADO-TIJOLO | B12: MODERADO | C12: TIJOLO | D12: 0.4
A13: =$B13&"-"&C13 -> MODERADO-FOFs | B13: MODERADO | C13: FOFs | D13: 0.1
A14: =$B14&"-"&C14 -> MODERADO-HIBRIDOS | B14: MODERADO | C14: HIBRIDOS | D14: 0.08
A15: =$B15&"-"&C15 -> MODERADO-DESENVOLVIMENTO | B15: MODERADO | C15: DESENVOLVIMENTO | D15: 0.05
A16: =$B16&"-"&C16 -> MODERADO-HOTELARIAS | B16: MODERADO | C16: HOTELARIAS | D16: 0.05
... A22: =$B22&"-"&C22 -> AGRESSIVO-HOTELARIAS | B22: AGRESSIVO | C22: HOTELARIAS | D22: 0.1
